benigne/__init__.py
benigne/ft_filter.py
benigne/get_args.py
benigne/load_image.py
benigne-0.1.1.dist-info/METADATA
benigne-0.1.1.dist-info/WHEEL
benigne-0.1.1.dist-info/licenses/LICENSE
benigne-0.1.1.dist-info/RECORD
