Metadata-Version: 2.4
Name: benigne
Version: 0.1.1
Summary: Personnal features
Project-URL: Homepage, https://github.com/BenigneDemetz
Author-email: Benigne Demetz <benignedemetz@benigne.dev>
License-Expression: MIT
License-File: LICENSE
Classifier: Operating System :: OS Independent
Classifier: Programming Language :: Python :: 3
Requires-Python: >=3.8
